{"is_source_file": true, "format": "JavaScript", "description": "This file defines a function setupCounter that initializes a counter on a webpage element, updates the display, and adds click event handling to increment the counter.", "external_files": [], "external_methods": [], "published": ["setupCounter"], "classes": [], "methods": [{"name": "setupCounter(element)", "description": "Initializes a counter on a DOM element, updates its display, and sets up click event handling to increment the counter.", "scope": "", "scopeKind": ""}], "calls": ["element.addEventListener", "setCounter"], "search-terms": ["counter", "setupCounter", "click event", "DOM manipulation", "JavaScript event handling"], "state": 2, "file_id": 8, "knowledge_revision": 19, "git_revision": "5b72db6b4e431a5c8242848b66fddb5a09e05660", "ctags": [{"_type": "tag", "name": "setupCounter", "path": "/home/kavia/workspace/code-generation/match-master-48246-48255/game_frontend/src/counter.js", "pattern": "/^export function setupCounter(element) {$/", "language": "JavaScript", "kind": "function", "signature": "(element)"}], "hash": "2ac86fab0c68ff8890db658663b5b7f5", "format-version": 4, "code-base-name": "game_frontend", "filename": "game_frontend/src/counter.js", "revision_history": [{"19": "5b72db6b4e431a5c8242848b66fddb5a09e05660"}]}